ffcount/__version__.py
ffcount/count.cpython-311-aarch64-linux-gnu.so
ffcount/__init__.py
ffcount/py.typed
ffcount/__main__.py
ffcount/count.pyi
ffcount-0.2.3.dist-info/LICENSE
ffcount-0.2.3.dist-info/WHEEL
ffcount-0.2.3.dist-info/METADATA
ffcount-0.2.3.dist-info/top_level.txt
ffcount-0.2.3.dist-info/RECORD
ffcount-0.2.3.dist-info/entry_points.txt
