Metadata-Version: 2.2
Name: ffcount
Version: 0.2.3
Summary: Fast File Count: Recursively count files and directories very quickly
Home-page: https://github.com/GjjvdBurg/ffcount
Author: G.J.J. van den Burg
Author-email: gertjanvandenburg@gmail.com
License: Apache License 2.0
Classifier: License :: OSI Approved :: Apache Software License
Classifier: Programming Language :: Python :: 3
Classifier: Topic :: Utilities
License-File: LICENSE
Dynamic: author
Dynamic: author-email
Dynamic: classifier
Dynamic: description
Dynamic: description-content-type
Dynamic: home-page
Dynamic: license
Dynamic: summary
